{"format":{"tagTypes":["ID3v2.3"],"trackInfo":[],"lossless":false,"container":"MPEG","codec":"MPEG 1 Layer 3","sampleRate":44100,"numberOfChannels":2,"bitrate":190552.0004145937,"tool":"LAME 3.97b","trackPeakLevel":null,"trackGain":-2.5,"duration":141.7665306122449,"codecProfile":"V0"},"native":{"ID3v2.3":[{"id":"TSSE","value":"Lame V3.97 (Beta)"},{"id":"TIT2","value":"Track 25"},{"id":"TPE1","value":"Free Matter For The Blind"},{"id":"TALB","value":"Audio Zine 5"},{"id":"COMM","value":{"language":"XXX","descriptor":"","text":"\"\""}},{"id":"TRCK","value":"25"}]},"quality":{"warnings":[{"message":"Invalid ID3v2.3 frame-header-ID: \u0000\u0000\u0000\u0000"},{"message":"id3v2.3 header has empty tag type=\u0000\u0000\u0000\u0000"},{"message":"Invalid ID3v2.3 frame-header-ID: \u0000\u0000\u0000\u0000"},{"message":"id3v2.3 header has empty tag type=\u0000\u0000\u0000\u0000"},{"message":"Invalid ID3v2.3 frame-header-ID: \u0000\u0000\u0000\u0000"},{"message":"id3v2.3 header has empty tag type=\u0000\u0000\u0000\u0000"},{"message":"Invalid ID3v2.3 frame-header-ID: \u0000\u0000\u0000\u0000"},{"message":"id3v2.3 header has empty tag type=\u0000\u0000\u0000\u0000"},{"message":"Invalid ID3v2.3 frame-header-ID: \u0000\u0000\u0000\u0000"},{"message":"id3v2.3 header has empty tag type=\u0000\u0000\u0000\u0000"},{"message":"Invalid ID3v2.3 frame-header-ID: \u0000\u0000\u0000\u0000"},{"message":"id3v2.3 header has empty tag type=\u0000\u0000\u0000\u0000"},{"message":"Invalid ID3v2.3 frame-header-ID: \u0000\u0000\u0000\u0000"},{"message":"id3v2.3 header has empty tag type=\u0000\u0000\u0000\u0000"},{"message":"Invalid ID3v2.3 frame-header-ID: \u0000\u0000\u0000\u0000"},{"message":"id3v2.3 header has empty tag type=\u0000\u0000\u0000\u0000"},{"message":"Invalid ID3v2.3 frame-header-ID: \u0000\u0000\u0000\u0000"},{"message":"id3v2.3 header has empty tag type=\u0000\u0000\u0000\u0000"},{"message":"Invalid ID3v2.3 frame-header-ID: \u0000\u0000\u0000\u0000"},{"message":"id3v2.3 header has empty tag type=\u0000\u0000\u0000\u0000"},{"message":"Invalid ID3v2.3 frame-header-ID: \u0000\u0000\u0000\u0000"},{"message":"id3v2.3 header has empty tag type=\u0000\u0000\u0000\u0000"},{"message":"Invalid ID3v2.3 frame-header-ID: \u0000\u0000\u0000\u0000"},{"message":"id3v2.3 header has empty tag type=\u0000\u0000\u0000\u0000"},{"message":"Invalid ID3v2.3 frame-header-ID: \u0000\u0000\u0000\u0000"},{"message":"id3v2.3 header has empty tag type=\u0000\u0000\u0000\u0000"},{"message":"Invalid ID3v2.3 frame-header-ID: \u0000\u0000\u0000\u0000"},{"message":"id3v2.3 header has empty tag type=\u0000\u0000\u0000\u0000"},{"message":"Invalid ID3v2.3 frame-header-ID: \u0000\u0000\u0000\u0000"},{"message":"id3v2.3 header has empty tag type=\u0000\u0000\u0000\u0000"},{"message":"Invalid ID3v2.3 frame-header-ID: \u0000\u0000\u0000\u0000"},{"message":"id3v2.3 header has empty tag type=\u0000\u0000\u0000\u0000"},{"message":"Invalid ID3v2.3 frame-header-ID: \u0000\u0000\u0000\u0000"},{"message":"id3v2.3 header has empty tag type=\u0000\u0000\u0000\u0000"},{"message":"Invalid ID3v2.3 frame-header-ID: \u0000\u0000\u0000\u0000"},{"message":"id3v2.3 header has empty tag type=\u0000\u0000\u0000\u0000"},{"message":"Invalid ID3v2.3 frame-header-ID: \u0000\u0000\u0000\u0000"},{"message":"id3v2.3 header has empty tag type=\u0000\u0000\u0000\u0000"},{"message":"Invalid ID3v2.3 frame-header-ID: \u0000\u0000\u0000\u0000"},{"message":"id3v2.3 header has empty tag type=\u0000\u0000\u0000\u0000"},{"message":"Invalid ID3v2.3 frame-header-ID: \u0000\u0000\u0000\u0000"},{"message":"id3v2.3 header has empty tag type=\u0000\u0000\u0000\u0000"},{"message":"Invalid ID3v2.3 frame-header-ID: \u0000\u0000\u0000\u0000"},{"message":"id3v2.3 header has empty tag type=\u0000\u0000\u0000\u0000"},{"message":"Invalid ID3v2.3 frame-header-ID: \u0000\u0000\u0000\u0000"},{"message":"id3v2.3 header has empty tag type=\u0000\u0000\u0000\u0000"},{"message":"Invalid ID3v2.3 frame-header-ID: \u0000\u0000\u0000\u0000"},{"message":"id3v2.3 header has empty tag type=\u0000\u0000\u0000\u0000"},{"message":"Invalid ID3v2.3 frame-header-ID: \u0000\u0000\u0000\u0000"},{"message":"id3v2.3 header has empty tag type=\u0000\u0000\u0000\u0000"},{"message":"Invalid ID3v2.3 frame-header-ID: \u0000\u0000\u0000\u0000"},{"message":"id3v2.3 header has empty tag type=\u0000\u0000\u0000\u0000"},{"message":"Illegal ID3v2 tag length"}]},"common":{"track":{"no":25,"of":null},"disk":{"no":null,"of":null},"movementIndex":{"no":null,"of":null},"encodersettings":"Lame V3.97 (Beta)","title":"Track 25","artists":["Free Matter For The Blind"],"artist":"Free Matter For The Blind","album":"Audio Zine 5","comment":[{"language":"XXX","descriptor":"","text":"\"\""}]}}