{"name":"Pillow Fight In Hell","album":{"name":"Cod Is My Go Pilot","path":"/artists/bornpilot/cod-is-my-go-pilot"},"artist":{"name":"Bornpilot","path":"/artists/bornpilot"},"path":"/artists/bornpilot/cod-is-my-go-pilot/pillow-fight-in-hell","metadata":{"format":{"tagTypes":["APEv2"],"trackInfo":[],"lossless":false,"container":"MPEG","codec":"MPEG 1 Layer 3","sampleRate":44100,"numberOfChannels":2,"bitrate":128000,"codecProfile":"CBR","numberOfSamples":2822400,"duration":64},"native":{"APEv2":[{"id":"ALBUM","value":"Cod Is My Go Pilot"},{"id":"ARTIST","value":"Bornpilot"},{"id":"TITLE","value":"Pillow Fight In Hell"},{"id":"TRACK","value":"5"}]},"quality":{"warnings":[]},"common":{"track":{"no":5,"of":null},"disk":{"no":null,"of":null},"movementIndex":{"no":null,"of":null},"album":"Cod Is My Go Pilot","artists":["Bornpilot"],"artist":"Bornpilot","title":"Pillow Fight In Hell"}}}