{"name":"Forever Flock","album":{"name":"Vidooch","path":"/artists/vidooch/vidooch"},"artist":{"name":"Vidooch","path":"/artists/vidooch"},"path":"/artists/vidooch/vidooch/forever-flock","metadata":{"format":{"tagTypes":["APEv2"],"trackInfo":[],"lossless":false,"container":"MPEG","codec":"MPEG 1 Layer 3","sampleRate":44100,"numberOfChannels":2,"bitrate":128000,"codecProfile":"CBR","tool":"LAME 3.96r","trackPeakLevel":null,"duration":243.1477551020408},"native":{"APEv2":[{"id":"ALBUM","value":"Vidooch"},{"id":"ARTIST","value":"Vidooch"},{"id":"TITLE","value":"Forever Flock"},{"id":"TRACK","value":"4"}]},"quality":{"warnings":[]},"common":{"track":{"no":4,"of":null},"disk":{"no":null,"of":null},"movementIndex":{"no":null,"of":null},"album":"Vidooch","artists":["Vidooch"],"artist":"Vidooch","title":"Forever Flock"}}}