{"format":{"tagTypes":["ID3v2.3"],"trackInfo":[],"lossless":false,"container":"MPEG","codec":"MPEG 2 Layer 3","sampleRate":22050,"numberOfChannels":2,"bitrate":56000,"codecProfile":"CBR","numberOfSamples":3115584,"duration":141.29632653061225},"native":{"ID3v2.3":[{"id":"TIT2","value":"Shores Of Nova"},{"id":"TPE1","value":"The Barco Project"},{"id":"TALB","value":"Two"}]},"quality":{"warnings":[{"message":"Invalid ID3v2.3 frame-header-ID: \u0000\u0000\u0000\u0000"},{"message":"id3v2.3 header has empty tag type=\u0000\u0000\u0000\u0000"},{"message":"Invalid ID3v2.3 frame-header-ID: \u0000\u0000\u0000\u0000"},{"message":"id3v2.3 header has empty tag type=\u0000\u0000\u0000\u0000"},{"message":"Invalid ID3v2.3 frame-header-ID: \u0000\u0000\u0000\u0000"},{"message":"id3v2.3 header has empty tag type=\u0000\u0000\u0000\u0000"},{"message":"Invalid ID3v2.3 frame-header-ID: \u0000\u0000\u0000\u0000"},{"message":"id3v2.3 header has empty tag type=\u0000\u0000\u0000\u0000"},{"message":"Invalid ID3v2.3 frame-header-ID: \u0000\u0000\u0000\u0000"},{"message":"id3v2.3 header has empty tag type=\u0000\u0000\u0000\u0000"},{"message":"Invalid ID3v2.3 frame-header-ID: \u0000\u0000\u0000\u0000"},{"message":"id3v2.3 header has empty tag type=\u0000\u0000\u0000\u0000"},{"message":"Invalid ID3v2.3 frame-header-ID: \u0000\u0000\u0000\u0000"},{"message":"id3v2.3 header has empty tag type=\u0000\u0000\u0000\u0000"},{"message":"Invalid ID3v2.3 frame-header-ID: \u0000\u0000\u0000\u0000"},{"message":"id3v2.3 header has empty tag type=\u0000\u0000\u0000\u0000"},{"message":"Invalid ID3v2.3 frame-header-ID: \u0000\u0000\u0000\u0000"},{"message":"id3v2.3 header has empty tag type=\u0000\u0000\u0000\u0000"},{"message":"Invalid ID3v2.3 frame-header-ID: \u0000\u0000\u0000\u0000"},{"message":"id3v2.3 header has empty tag type=\u0000\u0000\u0000\u0000"},{"message":"Invalid ID3v2.3 frame-header-ID: \u0000\u0000\u0000\u0000"},{"message":"id3v2.3 header has empty tag type=\u0000\u0000\u0000\u0000"},{"message":"Invalid ID3v2.3 frame-header-ID: \u0000\u0000\u0000\u0000"},{"message":"id3v2.3 header has empty tag type=\u0000\u0000\u0000\u0000"},{"message":"Invalid ID3v2.3 frame-header-ID: \u0000\u0000\u0000\u0000"},{"message":"id3v2.3 header has empty tag type=\u0000\u0000\u0000\u0000"},{"message":"Invalid ID3v2.3 frame-header-ID: \u0000\u0000\u0000\u0000"},{"message":"id3v2.3 header has empty tag type=\u0000\u0000\u0000\u0000"},{"message":"Invalid ID3v2.3 frame-header-ID: \u0000\u0000\u0000\u0000"},{"message":"id3v2.3 header has empty tag type=\u0000\u0000\u0000\u0000"},{"message":"Invalid ID3v2.3 frame-header-ID: \u0000\u0000\u0000\u0000"},{"message":"id3v2.3 header has empty tag type=\u0000\u0000\u0000\u0000"},{"message":"Invalid ID3v2.3 frame-header-ID: \u0000\u0000\u0000\u0000"},{"message":"id3v2.3 header has empty tag type=\u0000\u0000\u0000\u0000"},{"message":"Invalid ID3v2.3 frame-header-ID: \u0000\u0000\u0000\u0000"},{"message":"id3v2.3 header has empty tag type=\u0000\u0000\u0000\u0000"},{"message":"Invalid ID3v2.3 frame-header-ID: \u0000\u0000\u0000\u0000"},{"message":"id3v2.3 header has empty tag type=\u0000\u0000\u0000\u0000"},{"message":"Invalid ID3v2.3 frame-header-ID: \u0000\u0000\u0000\u0000"},{"message":"id3v2.3 header has empty tag type=\u0000\u0000\u0000\u0000"},{"message":"Invalid ID3v2.3 frame-header-ID: \u0000\u0000\u0000\u0000"},{"message":"id3v2.3 header has empty tag type=\u0000\u0000\u0000\u0000"},{"message":"Invalid ID3v2.3 frame-header-ID: \u0000\u0000\u0000\u0000"},{"message":"id3v2.3 header has empty tag type=\u0000\u0000\u0000\u0000"},{"message":"Invalid ID3v2.3 frame-header-ID: \u0000\u0000\u0000\u0000"},{"message":"id3v2.3 header has empty tag type=\u0000\u0000\u0000\u0000"},{"message":"Invalid ID3v2.3 frame-header-ID: \u0000\u0000\u0000\u0000"},{"message":"id3v2.3 header has empty tag type=\u0000\u0000\u0000\u0000"},{"message":"Invalid ID3v2.3 frame-header-ID: \u0000\u0000\u0000\u0000"},{"message":"id3v2.3 header has empty tag type=\u0000\u0000\u0000\u0000"},{"message":"Invalid ID3v2.3 frame-header-ID: \u0000\u0000\u0000\u0000"},{"message":"id3v2.3 header has empty tag type=\u0000\u0000\u0000\u0000"},{"message":"Invalid ID3v2.3 frame-header-ID: \u0000\u0000\u0000\u0000"},{"message":"id3v2.3 header has empty tag type=\u0000\u0000\u0000\u0000"},{"message":"Invalid ID3v2.3 frame-header-ID: \u0000\u0000\u0000\u0000"},{"message":"id3v2.3 header has empty tag type=\u0000\u0000\u0000\u0000"},{"message":"Illegal ID3v2 tag length"}]},"common":{"track":{"no":null,"of":null},"disk":{"no":null,"of":null},"movementIndex":{"no":null,"of":null},"title":"Shores Of Nova","artists":["The Barco Project"],"artist":"The Barco Project","album":"Two"}}