{"name":"Kittens In My Dog Hole","album":{"name":"Tinkletitties","path":"/artists/vaginasaur/tinkletitties"},"artist":{"name":"Vaginasaur","path":"/artists/vaginasaur"},"path":"/artists/vaginasaur/tinkletitties/kittens-in-my-dog-hole","metadata":{"format":{"tagTypes":["APEv2"],"trackInfo":[],"lossless":false,"container":"MPEG","codec":"MPEG 1 Layer 3","sampleRate":44100,"numberOfChannels":2,"bitrate":128000,"codecProfile":"CBR","numberOfSamples":8606592,"duration":195.1608163265306},"native":{"APEv2":[{"id":"ALBUM","value":"Tinkletitties"},{"id":"ARTIST","value":"Vaginasaur"},{"id":"TITLE","value":"Kittens In My Dog Hole"},{"id":"TRACK","value":"7"}]},"quality":{"warnings":[]},"common":{"track":{"no":7,"of":null},"disk":{"no":null,"of":null},"movementIndex":{"no":null,"of":null},"album":"Tinkletitties","artists":["Vaginasaur"],"artist":"Vaginasaur","title":"Kittens In My Dog Hole"}}}