{"metadata":{"format":{"tagTypes":["APEv2"],"trackInfo":[],"lossless":false,"container":"MPEG","codec":"MPEG 1 Layer 3","sampleRate":44100,"numberOfChannels":2,"bitrate":128000,"codecProfile":"CBR","numberOfSamples":6256512,"duration":141.87102040816328},"native":{"APEv2":[{"id":"ALBUM","value":"Poke It"},{"id":"ARTIST","value":"Hot Buns And Tea"},{"id":"COMPOSER","value":"Ted Crawford"},{"id":"COMPOSER","value":"Mike Parry"},{"id":"COMPOSER","value":"Curt Howard"},{"id":"TITLE","value":"Cosmic Of Sorts"},{"id":"TRACK","value":"9"}]},"quality":{"warnings":[]},"common":{"track":{"no":9,"of":null},"disk":{"no":null,"of":null},"movementIndex":{"no":null,"of":null},"album":"Poke It","artists":["Hot Buns And Tea"],"artist":"Hot Buns And Tea","composer":["Ted Crawford","Mike Parry","Curt Howard"],"title":"Cosmic Of Sorts"}},"name":"Cosmic Of Sorts","path":"/artists/hot-buns-and-tea/poke-it/cosmic-of-sorts","filePath":"hot-buns-and-tea/poke-it/09-Cosmic-of-sorts.mp3","artistName":"Hot Buns And Tea","artistPath":"/artists/hot-buns-and-tea","albumName":"Poke It","albumPath":"/artists/hot-buns-and-tea/poke-it","members":[{"name":"Ted Crawford","path":"/members/ted-crawford"},{"name":"Mike Parry","path":"/members/mike-parry"},{"name":"Curt Howard","path":"/members/curt-howard"}],"trackNumber":9}