{"metadata":{"format":{"tagTypes":["APEv2"],"trackInfo":[],"lossless":false,"container":"MPEG","codec":"MPEG 1 Layer 3","sampleRate":44100,"numberOfChannels":2,"bitrate":192000,"codecProfile":"CBR","numberOfSamples":9468288,"duration":214.7004081632653},"native":{"APEv2":[{"id":"ALBUM","value":"Underground Epiphanies At High Speeds Prove Fatal"},{"id":"ARTIST","value":"Bear Is Driving"},{"id":"COMPOSER","value":"Erik Oshiem"},{"id":"COMPOSER","value":"Dan Consiglio"},{"id":"COMPOSER","value":"Corey Mark"},{"id":"COMPOSER","value":"Chris Conaway"},{"id":"TITLE","value":"Asymptotic Approach To Happiness"},{"id":"TRACK","value":"3"}]},"quality":{"warnings":[]},"common":{"track":{"no":3,"of":null},"disk":{"no":null,"of":null},"movementIndex":{"no":null,"of":null},"album":"Underground Epiphanies At High Speeds Prove Fatal","artists":["Bear Is Driving"],"artist":"Bear Is Driving","composer":["Erik Oshiem","Dan Consiglio","Corey Mark","Chris Conaway"],"title":"Asymptotic Approach To Happiness"}},"name":"Asymptotic Approach To Happiness","path":"/artists/bear-is-driving/underground-epiphanies-at-high-speeds-prove-fatal/asymptotic-approach-to-happiness","filePath":"bear-is-driving/underground-epiphanies-at-high-speeds-prove-fatal/03-Asymptotic-Approach-to-Happiness.mp3","artistName":"Bear Is Driving","artistPath":"/artists/bear-is-driving","albumName":"Underground Epiphanies At High Speeds Prove Fatal","albumPath":"/artists/bear-is-driving/underground-epiphanies-at-high-speeds-prove-fatal","members":[{"name":"Erik Oshiem","path":"/members/erik-oshiem"},{"name":"Dan Consiglio","path":"/members/dan-consiglio"},{"name":"Corey Mark","path":"/members/corey-mark"},{"name":"Chris Conaway","path":"/members/chris-conaway"}],"trackNumber":3}