{"format":{"tagTypes":["ID3v2.3"],"trackInfo":[],"lossless":false,"container":"MPEG","codec":"MPEG 1 Layer 3","sampleRate":44100,"numberOfChannels":2,"bitrate":192000,"codecProfile":"CBR","numberOfSamples":11750400,"duration":266.44897959183675},"native":{"ID3v2.3":[{"id":"TYER","value":""},{"id":"TRCK","value":"7"},{"id":"TPE1","value":"J. Mono"},{"id":"TIT2","value":"Into the Sun Pt 5"},{"id":"TALB","value":"The Cold Lamper / J. Mono Split"}]},"quality":{"warnings":[{"message":"Invalid ID3v2.3 frame-header-ID: \u0000\u0000\u0000\u0000"},{"message":"id3v2.3 header has empty tag type=\u0000\u0000\u0000\u0000"},{"message":"Invalid ID3v2.3 frame-header-ID: \u0000\u0000\u0000\u0000"},{"message":"id3v2.3 header has empty tag type=\u0000\u0000\u0000\u0000"},{"message":"Invalid ID3v2.3 frame-header-ID: \u0000\u0000\u0000\u0000"},{"message":"id3v2.3 header has empty tag type=\u0000\u0000\u0000\u0000"},{"message":"Invalid ID3v2.3 frame-header-ID: \u0000\u0000\u0000\u0000"},{"message":"id3v2.3 header has empty tag type=\u0000\u0000\u0000\u0000"},{"message":"Invalid ID3v2.3 frame-header-ID: \u0000\u0000\u0000\u0000"},{"message":"id3v2.3 header has empty tag type=\u0000\u0000\u0000\u0000"},{"message":"Invalid ID3v2.3 frame-header-ID: \u0000\u0000\u0000\u0000"},{"message":"id3v2.3 header has empty tag type=\u0000\u0000\u0000\u0000"},{"message":"Invalid ID3v2.3 frame-header-ID: \u0000\u0000\u0000\u0000"},{"message":"id3v2.3 header has empty tag type=\u0000\u0000\u0000\u0000"},{"message":"Invalid ID3v2.3 frame-header-ID: \u0000\u0000\u0000\u0000"},{"message":"id3v2.3 header has empty tag type=\u0000\u0000\u0000\u0000"},{"message":"Invalid ID3v2.3 frame-header-ID: \u0000\u0000\u0000\u0000"},{"message":"id3v2.3 header has empty tag type=\u0000\u0000\u0000\u0000"},{"message":"Invalid ID3v2.3 frame-header-ID: \u0000\u0000\u0000\u0000"},{"message":"id3v2.3 header has empty tag type=\u0000\u0000\u0000\u0000"},{"message":"Invalid ID3v2.3 frame-header-ID: \u0000\u0000\u0000\u0000"},{"message":"id3v2.3 header has empty tag type=\u0000\u0000\u0000\u0000"},{"message":"Invalid ID3v2.3 frame-header-ID: \u0000\u0000\u0000\u0000"},{"message":"id3v2.3 header has empty tag type=\u0000\u0000\u0000\u0000"},{"message":"Invalid ID3v2.3 frame-header-ID: \u0000\u0000\u0000\u0000"},{"message":"id3v2.3 header has empty tag type=\u0000\u0000\u0000\u0000"},{"message":"Invalid ID3v2.3 frame-header-ID: \u0000\u0000\u0000\u0000"},{"message":"id3v2.3 header has empty tag type=\u0000\u0000\u0000\u0000"},{"message":"Invalid ID3v2.3 frame-header-ID: \u0000\u0000\u0000\u0000"},{"message":"id3v2.3 header has empty tag type=\u0000\u0000\u0000\u0000"},{"message":"Invalid ID3v2.3 frame-header-ID: \u0000\u0000\u0000\u0000"},{"message":"id3v2.3 header has empty tag type=\u0000\u0000\u0000\u0000"},{"message":"Invalid ID3v2.3 frame-header-ID: \u0000\u0000\u0000\u0000"},{"message":"id3v2.3 header has empty tag type=\u0000\u0000\u0000\u0000"},{"message":"Invalid ID3v2.3 frame-header-ID: \u0000\u0000\u0000\u0000"},{"message":"id3v2.3 header has empty tag type=\u0000\u0000\u0000\u0000"},{"message":"Invalid ID3v2.3 frame-header-ID: \u0000\u0000\u0000\u0000"},{"message":"id3v2.3 header has empty tag type=\u0000\u0000\u0000\u0000"},{"message":"Invalid ID3v2.3 frame-header-ID: \u0000\u0000\u0000\u0000"},{"message":"id3v2.3 header has empty tag type=\u0000\u0000\u0000\u0000"},{"message":"Invalid ID3v2.3 frame-header-ID: \u0000\u0000\u0000\u0000"},{"message":"id3v2.3 header has empty tag type=\u0000\u0000\u0000\u0000"},{"message":"Invalid ID3v2.3 frame-header-ID: \u0000\u0000\u0000\u0000"},{"message":"id3v2.3 header has empty tag type=\u0000\u0000\u0000\u0000"},{"message":"Invalid ID3v2.3 frame-header-ID: \u0000\u0000\u0000\u0000"},{"message":"id3v2.3 header has empty tag type=\u0000\u0000\u0000\u0000"},{"message":"Invalid ID3v2.3 frame-header-ID: \u0000\u0000\u0000\u0000"},{"message":"id3v2.3 header has empty tag type=\u0000\u0000\u0000\u0000"},{"message":"Invalid ID3v2.3 frame-header-ID: \u0000\u0000\u0000\u0000"},{"message":"id3v2.3 header has empty tag type=\u0000\u0000\u0000\u0000"},{"message":"Invalid ID3v2.3 frame-header-ID: \u0000\u0000\u0000\u0000"},{"message":"id3v2.3 header has empty tag type=\u0000\u0000\u0000\u0000"},{"message":"Invalid ID3v2.3 frame-header-ID: \u0000\u0000\u0000\u0000"},{"message":"id3v2.3 header has empty tag type=\u0000\u0000\u0000\u0000"},{"message":"Invalid ID3v2.3 frame-header-ID: \u0000\u0000\u0000\u0000"},{"message":"id3v2.3 header has empty tag type=\u0000\u0000\u0000\u0000"},{"message":"Invalid ID3v2.3 frame-header-ID: \u0000\u0000\u0000\u0000"},{"message":"id3v2.3 header has empty tag type=\u0000\u0000\u0000\u0000"},{"message":"Invalid ID3v2.3 frame-header-ID: \u0000\u0000\u0000\u0000"},{"message":"id3v2.3 header has empty tag type=\u0000\u0000\u0000\u0000"},{"message":"Invalid ID3v2.3 frame-header-ID: \u0000\u0000\u0000\u0000"},{"message":"id3v2.3 header has empty tag type=\u0000\u0000\u0000\u0000"},{"message":"Invalid ID3v2.3 frame-header-ID: \u0000\u0000\u0000\u0000"},{"message":"id3v2.3 header has empty tag type=\u0000\u0000\u0000\u0000"},{"message":"Invalid ID3v2.3 frame-header-ID: \u0000\u0000\u0000\u0000"},{"message":"id3v2.3 header has empty tag type=\u0000\u0000\u0000\u0000"},{"message":"Invalid ID3v2.3 frame-header-ID: \u0000\u0000\u0000\u0000"},{"message":"id3v2.3 header has empty tag type=\u0000\u0000\u0000\u0000"},{"message":"Invalid ID3v2.3 frame-header-ID: \u0000\u0000\u0000\u0000"},{"message":"id3v2.3 header has empty tag type=\u0000\u0000\u0000\u0000"},{"message":"Invalid ID3v2.3 frame-header-ID: \u0000\u0000\u0000\u0000"},{"message":"id3v2.3 header has empty tag type=\u0000\u0000\u0000\u0000"},{"message":"Invalid ID3v2.3 frame-header-ID: \u0000\u0000\u0000\u0000"},{"message":"id3v2.3 header has empty tag type=\u0000\u0000\u0000\u0000"},{"message":"Invalid ID3v2.3 frame-header-ID: \u0000\u0000\u0000\u0000"},{"message":"id3v2.3 header has empty tag type=\u0000\u0000\u0000\u0000"},{"message":"Invalid ID3v2.3 frame-header-ID: \u0000\u0000\u0000\u0000"},{"message":"id3v2.3 header has empty tag type=\u0000\u0000\u0000\u0000"},{"message":"Invalid ID3v2.3 frame-header-ID: \u0000\u0000\u0000\u0000"},{"message":"id3v2.3 header has empty tag type=\u0000\u0000\u0000\u0000"},{"message":"Invalid ID3v2.3 frame-header-ID: \u0000\u0000\u0000\u0000"},{"message":"id3v2.3 header has empty tag type=\u0000\u0000\u0000\u0000"},{"message":"Invalid ID3v2.3 frame-header-ID: \u0000\u0000\u0000\u0000"},{"message":"id3v2.3 header has empty tag type=\u0000\u0000\u0000\u0000"},{"message":"Invalid ID3v2.3 frame-header-ID: \u0000\u0000\u0000\u0000"},{"message":"id3v2.3 header has empty tag type=\u0000\u0000\u0000\u0000"},{"message":"Invalid ID3v2.3 frame-header-ID: \u0000\u0000\u0000\u0000"},{"message":"id3v2.3 header has empty tag type=\u0000\u0000\u0000\u0000"},{"message":"Invalid ID3v2.3 frame-header-ID: \u0000\u0000\u0000\u0000"},{"message":"id3v2.3 header has empty tag type=\u0000\u0000\u0000\u0000"},{"message":"Invalid ID3v2.3 frame-header-ID: \u0000\u0000\u0000\u0000"},{"message":"id3v2.3 header has empty tag type=\u0000\u0000\u0000\u0000"},{"message":"Invalid ID3v2.3 frame-header-ID: \u0000\u0000\u0000\u0000"},{"message":"id3v2.3 header has empty tag type=\u0000\u0000\u0000\u0000"},{"message":"Invalid ID3v2.3 frame-header-ID: \u0000\u0000\u0000\u0000"},{"message":"id3v2.3 header has empty tag type=\u0000\u0000\u0000\u0000"},{"message":"Invalid ID3v2.3 frame-header-ID: \u0000\u0000\u0000\u0000"},{"message":"id3v2.3 header has empty tag type=\u0000\u0000\u0000\u0000"},{"message":"Invalid ID3v2.3 frame-header-ID: \u0000\u0000\u0000\u0000"},{"message":"id3v2.3 header has empty tag type=\u0000\u0000\u0000\u0000"},{"message":"Invalid ID3v2.3 frame-header-ID: \u0000\u0000\u0000\u0000"},{"message":"id3v2.3 header has empty tag type=\u0000\u0000\u0000\u0000"},{"message":"Invalid ID3v2.3 frame-header-ID: \u0000\u0000\u0000\u0000"},{"message":"id3v2.3 header has empty tag type=\u0000\u0000\u0000\u0000"},{"message":"Invalid ID3v2.3 frame-header-ID: \u0000\u0000\u0000\u0000"},{"message":"id3v2.3 header has empty tag type=\u0000\u0000\u0000\u0000"},{"message":"Invalid ID3v2.3 frame-header-ID: \u0000\u0000\u0000\u0000"},{"message":"id3v2.3 header has empty tag type=\u0000\u0000\u0000\u0000"},{"message":"Invalid ID3v2.3 frame-header-ID: \u0000\u0000\u0000\u0000"},{"message":"id3v2.3 header has empty tag type=\u0000\u0000\u0000\u0000"},{"message":"Invalid ID3v2.3 frame-header-ID: \u0000\u0000\u0000\u0000"},{"message":"id3v2.3 header has empty tag type=\u0000\u0000\u0000\u0000"},{"message":"Invalid ID3v2.3 frame-header-ID: \u0000\u0000\u0000\u0000"},{"message":"id3v2.3 header has empty tag type=\u0000\u0000\u0000\u0000"},{"message":"Invalid ID3v2.3 frame-header-ID: \u0000\u0000\u0000\u0000"},{"message":"id3v2.3 header has empty tag type=\u0000\u0000\u0000\u0000"},{"message":"Invalid ID3v2.3 frame-header-ID: \u0000\u0000\u0000\u0000"},{"message":"id3v2.3 header has empty tag type=\u0000\u0000\u0000\u0000"},{"message":"Invalid ID3v2.3 frame-header-ID: \u0000\u0000\u0000\u0000"},{"message":"id3v2.3 header has empty tag type=\u0000\u0000\u0000\u0000"},{"message":"Invalid ID3v2.3 frame-header-ID: \u0000\u0000\u0000\u0000"},{"message":"id3v2.3 header has empty tag type=\u0000\u0000\u0000\u0000"},{"message":"Invalid ID3v2.3 frame-header-ID: \u0000\u0000\u0000\u0000"},{"message":"id3v2.3 header has empty tag type=\u0000\u0000\u0000\u0000"},{"message":"Invalid ID3v2.3 frame-header-ID: \u0000\u0000\u0000\u0000"},{"message":"id3v2.3 header has empty tag type=\u0000\u0000\u0000\u0000"},{"message":"Invalid ID3v2.3 frame-header-ID: \u0000\u0000\u0000\u0000"},{"message":"id3v2.3 header has empty tag type=\u0000\u0000\u0000\u0000"},{"message":"Invalid ID3v2.3 frame-header-ID: \u0000\u0000\u0000\u0000"},{"message":"id3v2.3 header has empty tag type=\u0000\u0000\u0000\u0000"},{"message":"Invalid ID3v2.3 frame-header-ID: \u0000\u0000\u0000\u0000"},{"message":"id3v2.3 header has empty tag type=\u0000\u0000\u0000\u0000"},{"message":"Invalid ID3v2.3 frame-header-ID: \u0000\u0000\u0000\u0000"},{"message":"id3v2.3 header has empty tag type=\u0000\u0000\u0000\u0000"},{"message":"Invalid ID3v2.3 frame-header-ID: \u0000\u0000\u0000\u0000"},{"message":"id3v2.3 header has empty tag type=\u0000\u0000\u0000\u0000"},{"message":"Invalid ID3v2.3 frame-header-ID: \u0000\u0000\u0000\u0000"},{"message":"id3v2.3 header has empty tag type=\u0000\u0000\u0000\u0000"},{"message":"Invalid ID3v2.3 frame-header-ID: \u0000\u0000\u0000\u0000"},{"message":"id3v2.3 header has empty tag type=\u0000\u0000\u0000\u0000"},{"message":"Invalid ID3v2.3 frame-header-ID: \u0000\u0000\u0000\u0000"},{"message":"id3v2.3 header has empty tag type=\u0000\u0000\u0000\u0000"},{"message":"Invalid ID3v2.3 frame-header-ID: \u0000\u0000\u0000\u0000"},{"message":"id3v2.3 header has empty tag type=\u0000\u0000\u0000\u0000"},{"message":"Invalid ID3v2.3 frame-header-ID: \u0000\u0000\u0000\u0000"},{"message":"id3v2.3 header has empty tag type=\u0000\u0000\u0000\u0000"},{"message":"Invalid ID3v2.3 frame-header-ID: \u0000\u0000\u0000\u0000"},{"message":"id3v2.3 header has empty tag type=\u0000\u0000\u0000\u0000"},{"message":"Invalid ID3v2.3 frame-header-ID: \u0000\u0000\u0000\u0000"},{"message":"id3v2.3 header has empty tag type=\u0000\u0000\u0000\u0000"},{"message":"Invalid ID3v2.3 frame-header-ID: \u0000\u0000\u0000\u0000"},{"message":"id3v2.3 header has empty tag type=\u0000\u0000\u0000\u0000"},{"message":"Invalid ID3v2.3 frame-header-ID: \u0000\u0000\u0000\u0000"},{"message":"id3v2.3 header has empty tag type=\u0000\u0000\u0000\u0000"},{"message":"Invalid ID3v2.3 frame-header-ID: \u0000\u0000\u0000\u0000"},{"message":"id3v2.3 header has empty tag type=\u0000\u0000\u0000\u0000"},{"message":"Invalid ID3v2.3 frame-header-ID: \u0000\u0000\u0000\u0000"},{"message":"id3v2.3 header has empty tag type=\u0000\u0000\u0000\u0000"},{"message":"Invalid ID3v2.3 frame-header-ID: \u0000\u0000\u0000\u0000"},{"message":"id3v2.3 header has empty tag type=\u0000\u0000\u0000\u0000"},{"message":"Invalid ID3v2.3 frame-header-ID: \u0000\u0000\u0000\u0000"},{"message":"id3v2.3 header has empty tag type=\u0000\u0000\u0000\u0000"},{"message":"Invalid ID3v2.3 frame-header-ID: \u0000\u0000\u0000\u0000"},{"message":"id3v2.3 header has empty tag type=\u0000\u0000\u0000\u0000"},{"message":"Invalid ID3v2.3 frame-header-ID: \u0000\u0000\u0000\u0000"},{"message":"id3v2.3 header has empty tag type=\u0000\u0000\u0000\u0000"},{"message":"Invalid ID3v2.3 frame-header-ID: \u0000\u0000\u0000\u0000"},{"message":"id3v2.3 header has empty tag type=\u0000\u0000\u0000\u0000"},{"message":"Invalid ID3v2.3 frame-header-ID: \u0000\u0000\u0000\u0000"},{"message":"id3v2.3 header has empty tag type=\u0000\u0000\u0000\u0000"},{"message":"Invalid ID3v2.3 frame-header-ID: \u0000\u0000\u0000\u0000"},{"message":"id3v2.3 header has empty tag type=\u0000\u0000\u0000\u0000"},{"message":"Invalid ID3v2.3 frame-header-ID: \u0000\u0000\u0000\u0000"},{"message":"id3v2.3 header has empty tag type=\u0000\u0000\u0000\u0000"},{"message":"Invalid ID3v2.3 frame-header-ID: \u0000\u0000\u0000\u0000"},{"message":"id3v2.3 header has empty tag type=\u0000\u0000\u0000\u0000"},{"message":"Invalid ID3v2.3 frame-header-ID: \u0000\u0000\u0000\u0000"},{"message":"id3v2.3 header has empty tag type=\u0000\u0000\u0000\u0000"},{"message":"Invalid ID3v2.3 frame-header-ID: \u0000\u0000\u0000\u0000"},{"message":"id3v2.3 header has empty tag type=\u0000\u0000\u0000\u0000"},{"message":"Invalid ID3v2.3 frame-header-ID: \u0000\u0000\u0000\u0000"},{"message":"id3v2.3 header has empty tag type=\u0000\u0000\u0000\u0000"},{"message":"Invalid ID3v2.3 frame-header-ID: \u0000\u0000\u0000\u0000"},{"message":"id3v2.3 header has empty tag type=\u0000\u0000\u0000\u0000"},{"message":"Invalid ID3v2.3 frame-header-ID: \u0000\u0000\u0000\u0000"},{"message":"id3v2.3 header has empty tag type=\u0000\u0000\u0000\u0000"},{"message":"Invalid ID3v2.3 frame-header-ID: \u0000\u0000\u0000\u0000"},{"message":"id3v2.3 header has empty tag type=\u0000\u0000\u0000\u0000"},{"message":"Invalid ID3v2.3 frame-header-ID: \u0000\u0000\u0000\u0000"},{"message":"id3v2.3 header has empty tag type=\u0000\u0000\u0000\u0000"},{"message":"Invalid ID3v2.3 frame-header-ID: \u0000\u0000\u0000\u0000"},{"message":"id3v2.3 header has empty tag type=\u0000\u0000\u0000\u0000"},{"message":"Invalid ID3v2.3 frame-header-ID: \u0000\u0000\u0000\u0000"},{"message":"id3v2.3 header has empty tag type=\u0000\u0000\u0000\u0000"},{"message":"Invalid ID3v2.3 frame-header-ID: \u0000\u0000\u0000\u0000"},{"message":"id3v2.3 header has empty tag type=\u0000\u0000\u0000\u0000"},{"message":"Invalid ID3v2.3 frame-header-ID: \u0000\u0000\u0000\u0000"},{"message":"id3v2.3 header has empty tag type=\u0000\u0000\u0000\u0000"},{"message":"Invalid ID3v2.3 frame-header-ID: \u0000\u0000\u0000\u0000"},{"message":"id3v2.3 header has empty tag type=\u0000\u0000\u0000\u0000"},{"message":"Invalid ID3v2.3 frame-header-ID: \u0000\u0000\u0000\u0000"},{"message":"id3v2.3 header has empty tag type=\u0000\u0000\u0000\u0000"},{"message":"Invalid ID3v2.3 frame-header-ID: \u0000\u0000\u0000\u0000"},{"message":"id3v2.3 header has empty tag type=\u0000\u0000\u0000\u0000"},{"message":"Invalid ID3v2.3 frame-header-ID: \u0000\u0000\u0000\u0000"},{"message":"id3v2.3 header has empty tag type=\u0000\u0000\u0000\u0000"},{"message":"Invalid ID3v2.3 frame-header-ID: \u0000\u0000\u0000\u0000"},{"message":"id3v2.3 header has empty tag type=\u0000\u0000\u0000\u0000"},{"message":"Invalid ID3v2.3 frame-header-ID: \u0000\u0000\u0000\u0000"},{"message":"id3v2.3 header has empty tag type=\u0000\u0000\u0000\u0000"},{"message":"Invalid ID3v2.3 frame-header-ID: \u0000\u0000\u0000\u0000"},{"message":"id3v2.3 header has empty tag type=\u0000\u0000\u0000\u0000"},{"message":"Invalid ID3v2.3 frame-header-ID: \u0000\u0000\u0000\u0000"},{"message":"id3v2.3 header has empty tag type=\u0000\u0000\u0000\u0000"},{"message":"Invalid ID3v2.3 frame-header-ID: \u0000\u0000\u0000\u0000"},{"message":"id3v2.3 header has empty tag type=\u0000\u0000\u0000\u0000"},{"message":"Invalid ID3v2.3 frame-header-ID: \u0000\u0000\u0000\u0000"},{"message":"id3v2.3 header has empty tag type=\u0000\u0000\u0000\u0000"},{"message":"Invalid ID3v2.3 frame-header-ID: \u0000\u0000\u0000\u0000"},{"message":"id3v2.3 header has empty tag type=\u0000\u0000\u0000\u0000"},{"message":"Invalid ID3v2.3 frame-header-ID: \u0000\u0000\u0000\u0000"},{"message":"id3v2.3 header has empty tag type=\u0000\u0000\u0000\u0000"},{"message":"Invalid ID3v2.3 frame-header-ID: \u0000\u0000\u0000\u0000"},{"message":"id3v2.3 header has empty tag type=\u0000\u0000\u0000\u0000"},{"message":"Invalid ID3v2.3 frame-header-ID: \u0000\u0000\u0000\u0000"},{"message":"id3v2.3 header has empty tag type=\u0000\u0000\u0000\u0000"},{"message":"Invalid ID3v2.3 frame-header-ID: \u0000\u0000\u0000\u0000"},{"message":"id3v2.3 header has empty tag type=\u0000\u0000\u0000\u0000"},{"message":"Invalid ID3v2.3 frame-header-ID: \u0000\u0000\u0000\u0000"},{"message":"id3v2.3 header has empty tag type=\u0000\u0000\u0000\u0000"},{"message":"Invalid ID3v2.3 frame-header-ID: \u0000\u0000\u0000\u0000"},{"message":"id3v2.3 header has empty tag type=\u0000\u0000\u0000\u0000"},{"message":"Invalid ID3v2.3 frame-header-ID: \u0000\u0000\u0000\u0000"},{"message":"id3v2.3 header has empty tag type=\u0000\u0000\u0000\u0000"},{"message":"Invalid ID3v2.3 frame-header-ID: \u0000\u0000\u0000\u0000"},{"message":"id3v2.3 header has empty tag type=\u0000\u0000\u0000\u0000"},{"message":"Invalid ID3v2.3 frame-header-ID: \u0000\u0000\u0000\u0000"},{"message":"id3v2.3 header has empty tag type=\u0000\u0000\u0000\u0000"},{"message":"Invalid ID3v2.3 frame-header-ID: \u0000\u0000\u0000\u0000"},{"message":"id3v2.3 header has empty tag type=\u0000\u0000\u0000\u0000"},{"message":"Invalid ID3v2.3 frame-header-ID: \u0000\u0000\u0000\u0000"},{"message":"id3v2.3 header has empty tag type=\u0000\u0000\u0000\u0000"},{"message":"Invalid ID3v2.3 frame-header-ID: \u0000\u0000\u0000\u0000"},{"message":"id3v2.3 header has empty tag type=\u0000\u0000\u0000\u0000"},{"message":"Invalid ID3v2.3 frame-header-ID: \u0000\u0000\u0000\u0000"},{"message":"id3v2.3 header has empty tag type=\u0000\u0000\u0000\u0000"},{"message":"Invalid ID3v2.3 frame-header-ID: \u0000\u0000\u0000\u0000"},{"message":"id3v2.3 header has empty tag type=\u0000\u0000\u0000\u0000"},{"message":"Invalid ID3v2.3 frame-header-ID: \u0000\u0000\u0000\u0000"},{"message":"id3v2.3 header has empty tag type=\u0000\u0000\u0000\u0000"},{"message":"Invalid ID3v2.3 frame-header-ID: \u0000\u0000\u0000\u0000"},{"message":"id3v2.3 header has empty tag type=\u0000\u0000\u0000\u0000"},{"message":"Invalid ID3v2.3 frame-header-ID: \u0000\u0000\u0000\u0000"},{"message":"id3v2.3 header has empty tag type=\u0000\u0000\u0000\u0000"},{"message":"Invalid ID3v2.3 frame-header-ID: \u0000\u0000\u0000\u0000"},{"message":"id3v2.3 header has empty tag type=\u0000\u0000\u0000\u0000"},{"message":"Invalid ID3v2.3 frame-header-ID: \u0000\u0000\u0000\u0000"},{"message":"id3v2.3 header has empty tag type=\u0000\u0000\u0000\u0000"},{"message":"Invalid ID3v2.3 frame-header-ID: \u0000\u0000\u0000\u0000"},{"message":"id3v2.3 header has empty tag type=\u0000\u0000\u0000\u0000"},{"message":"Invalid ID3v2.3 frame-header-ID: \u0000\u0000\u0000\u0000"},{"message":"id3v2.3 header has empty tag type=\u0000\u0000\u0000\u0000"},{"message":"Invalid ID3v2.3 frame-header-ID: \u0000\u0000\u0000\u0000"},{"message":"id3v2.3 header has empty tag type=\u0000\u0000\u0000\u0000"},{"message":"Invalid ID3v2.3 frame-header-ID: \u0000\u0000\u0000\u0000"},{"message":"id3v2.3 header has empty tag type=\u0000\u0000\u0000\u0000"},{"message":"Invalid ID3v2.3 frame-header-ID: \u0000\u0000\u0000\u0000"},{"message":"id3v2.3 header has empty tag type=\u0000\u0000\u0000\u0000"},{"message":"Invalid ID3v2.3 frame-header-ID: \u0000\u0000\u0000\u0000"},{"message":"id3v2.3 header has empty tag type=\u0000\u0000\u0000\u0000"},{"message":"Invalid ID3v2.3 frame-header-ID: \u0000\u0000\u0000\u0000"},{"message":"id3v2.3 header has empty tag type=\u0000\u0000\u0000\u0000"},{"message":"Invalid ID3v2.3 frame-header-ID: \u0000\u0000\u0000\u0000"},{"message":"id3v2.3 header has empty tag type=\u0000\u0000\u0000\u0000"},{"message":"Invalid ID3v2.3 frame-header-ID: \u0000\u0000\u0000\u0000"},{"message":"id3v2.3 header has empty tag type=\u0000\u0000\u0000\u0000"},{"message":"Invalid ID3v2.3 frame-header-ID: \u0000\u0000\u0000\u0000"},{"message":"id3v2.3 header has empty tag type=\u0000\u0000\u0000\u0000"},{"message":"Invalid ID3v2.3 frame-header-ID: \u0000\u0000\u0000\u0000"},{"message":"id3v2.3 header has empty tag type=\u0000\u0000\u0000\u0000"},{"message":"Invalid ID3v2.3 frame-header-ID: \u0000\u0000\u0000\u0000"},{"message":"id3v2.3 header has empty tag type=\u0000\u0000\u0000\u0000"},{"message":"Invalid ID3v2.3 frame-header-ID: \u0000\u0000\u0000\u0000"},{"message":"id3v2.3 header has empty tag type=\u0000\u0000\u0000\u0000"},{"message":"Invalid ID3v2.3 frame-header-ID: \u0000\u0000\u0000\u0000"},{"message":"id3v2.3 header has empty tag type=\u0000\u0000\u0000\u0000"},{"message":"Invalid ID3v2.3 frame-header-ID: \u0000\u0000\u0000\u0000"},{"message":"id3v2.3 header has empty tag type=\u0000\u0000\u0000\u0000"},{"message":"Invalid ID3v2.3 frame-header-ID: \u0000\u0000\u0000\u0000"},{"message":"id3v2.3 header has empty tag type=\u0000\u0000\u0000\u0000"},{"message":"Invalid ID3v2.3 frame-header-ID: \u0000\u0000\u0000\u0000"},{"message":"id3v2.3 header has empty tag type=\u0000\u0000\u0000\u0000"},{"message":"Invalid ID3v2.3 frame-header-ID: \u0000\u0000\u0000\u0000"},{"message":"id3v2.3 header has empty tag type=\u0000\u0000\u0000\u0000"},{"message":"Invalid ID3v2.3 frame-header-ID: \u0000\u0000\u0000\u0000"},{"message":"id3v2.3 header has empty tag type=\u0000\u0000\u0000\u0000"},{"message":"Invalid ID3v2.3 frame-header-ID: \u0000\u0000\u0000\u0000"},{"message":"id3v2.3 header has empty tag type=\u0000\u0000\u0000\u0000"},{"message":"Invalid ID3v2.3 frame-header-ID: \u0000\u0000\u0000\u0000"},{"message":"id3v2.3 header has empty tag type=\u0000\u0000\u0000\u0000"},{"message":"Invalid ID3v2.3 frame-header-ID: \u0000\u0000\u0000\u0000"},{"message":"id3v2.3 header has empty tag type=\u0000\u0000\u0000\u0000"},{"message":"Invalid ID3v2.3 frame-header-ID: \u0000\u0000\u0000\u0000"},{"message":"id3v2.3 header has empty tag type=\u0000\u0000\u0000\u0000"},{"message":"Invalid ID3v2.3 frame-header-ID: \u0000\u0000\u0000\u0000"},{"message":"id3v2.3 header has empty tag type=\u0000\u0000\u0000\u0000"},{"message":"Invalid ID3v2.3 frame-header-ID: \u0000\u0000\u0000\u0000"},{"message":"id3v2.3 header has empty tag type=\u0000\u0000\u0000\u0000"},{"message":"Invalid ID3v2.3 frame-header-ID: \u0000\u0000\u0000\u0000"},{"message":"id3v2.3 header has empty tag type=\u0000\u0000\u0000\u0000"},{"message":"Invalid ID3v2.3 frame-header-ID: \u0000\u0000\u0000\u0000"},{"message":"id3v2.3 header has empty tag type=\u0000\u0000\u0000\u0000"},{"message":"Invalid ID3v2.3 frame-header-ID: \u0000\u0000\u0000\u0000"},{"message":"id3v2.3 header has empty tag type=\u0000\u0000\u0000\u0000"},{"message":"Invalid ID3v2.3 frame-header-ID: \u0000\u0000\u0000\u0000"},{"message":"id3v2.3 header has empty tag type=\u0000\u0000\u0000\u0000"},{"message":"Invalid ID3v2.3 frame-header-ID: \u0000\u0000\u0000\u0000"},{"message":"id3v2.3 header has empty tag type=\u0000\u0000\u0000\u0000"},{"message":"Invalid ID3v2.3 frame-header-ID: \u0000\u0000\u0000\u0000"},{"message":"id3v2.3 header has empty tag type=\u0000\u0000\u0000\u0000"},{"message":"Invalid ID3v2.3 frame-header-ID: \u0000\u0000\u0000\u0000"},{"message":"id3v2.3 header has empty tag type=\u0000\u0000\u0000\u0000"},{"message":"Invalid ID3v2.3 frame-header-ID: \u0000\u0000\u0000\u0000"},{"message":"id3v2.3 header has empty tag type=\u0000\u0000\u0000\u0000"},{"message":"Invalid ID3v2.3 frame-header-ID: \u0000\u0000\u0000\u0000"},{"message":"id3v2.3 header has empty tag type=\u0000\u0000\u0000\u0000"},{"message":"Invalid ID3v2.3 frame-header-ID: \u0000\u0000\u0000\u0000"},{"message":"id3v2.3 header has empty tag type=\u0000\u0000\u0000\u0000"},{"message":"Invalid ID3v2.3 frame-header-ID: \u0000\u0000\u0000\u0000"},{"message":"id3v2.3 header has empty tag type=\u0000\u0000\u0000\u0000"},{"message":"Invalid ID3v2.3 frame-header-ID: \u0000\u0000\u0000\u0000"},{"message":"id3v2.3 header has empty tag type=\u0000\u0000\u0000\u0000"},{"message":"Invalid ID3v2.3 frame-header-ID: \u0000\u0000\u0000\u0000"},{"message":"id3v2.3 header has empty tag type=\u0000\u0000\u0000\u0000"},{"message":"Invalid ID3v2.3 frame-header-ID: \u0000\u0000\u0000\u0000"},{"message":"id3v2.3 header has empty tag type=\u0000\u0000\u0000\u0000"},{"message":"Invalid ID3v2.3 frame-header-ID: \u0000\u0000\u0000\u0000"},{"message":"id3v2.3 header has empty tag type=\u0000\u0000\u0000\u0000"},{"message":"Invalid ID3v2.3 frame-header-ID: \u0000\u0000\u0000\u0000"},{"message":"id3v2.3 header has empty tag type=\u0000\u0000\u0000\u0000"},{"message":"Invalid ID3v2.3 frame-header-ID: \u0000\u0000\u0000\u0000"},{"message":"id3v2.3 header has empty tag type=\u0000\u0000\u0000\u0000"},{"message":"Invalid ID3v2.3 frame-header-ID: \u0000\u0000\u0000\u0000"},{"message":"id3v2.3 header has empty tag type=\u0000\u0000\u0000\u0000"},{"message":"Invalid ID3v2.3 frame-header-ID: \u0000\u0000\u0000\u0000"},{"message":"id3v2.3 header has empty tag type=\u0000\u0000\u0000\u0000"},{"message":"Invalid ID3v2.3 frame-header-ID: \u0000\u0000\u0000\u0000"},{"message":"id3v2.3 header has empty tag type=\u0000\u0000\u0000\u0000"},{"message":"Invalid ID3v2.3 frame-header-ID: \u0000\u0000\u0000\u0000"},{"message":"id3v2.3 header has empty tag type=\u0000\u0000\u0000\u0000"},{"message":"Invalid ID3v2.3 frame-header-ID: \u0000\u0000\u0000\u0000"},{"message":"id3v2.3 header has empty tag type=\u0000\u0000\u0000\u0000"},{"message":"Invalid ID3v2.3 frame-header-ID: \u0000\u0000\u0000\u0000"},{"message":"id3v2.3 header has empty tag type=\u0000\u0000\u0000\u0000"},{"message":"Invalid ID3v2.3 frame-header-ID: \u0000\u0000\u0000\u0000"},{"message":"id3v2.3 header has empty tag type=\u0000\u0000\u0000\u0000"},{"message":"Invalid ID3v2.3 frame-header-ID: \u0000\u0000\u0000\u0000"},{"message":"id3v2.3 header has empty tag type=\u0000\u0000\u0000\u0000"},{"message":"Invalid ID3v2.3 frame-header-ID: \u0000\u0000\u0000\u0000"},{"message":"id3v2.3 header has empty tag type=\u0000\u0000\u0000\u0000"},{"message":"Invalid ID3v2.3 frame-header-ID: \u0000\u0000\u0000\u0000"},{"message":"id3v2.3 header has empty tag type=\u0000\u0000\u0000\u0000"},{"message":"Invalid ID3v2.3 frame-header-ID: \u0000\u0000\u0000\u0000"},{"message":"id3v2.3 header has empty tag type=\u0000\u0000\u0000\u0000"},{"message":"Invalid ID3v2.3 frame-header-ID: \u0000\u0000\u0000\u0000"},{"message":"id3v2.3 header has empty tag type=\u0000\u0000\u0000\u0000"},{"message":"Invalid ID3v2.3 frame-header-ID: \u0000\u0000\u0000\u0000"},{"message":"id3v2.3 header has empty tag type=\u0000\u0000\u0000\u0000"},{"message":"Invalid ID3v2.3 frame-header-ID: \u0000\u0000\u0000\u0000"},{"message":"id3v2.3 header has empty tag type=\u0000\u0000\u0000\u0000"},{"message":"Invalid ID3v2.3 frame-header-ID: \u0000\u0000\u0000\u0000"},{"message":"id3v2.3 header has empty tag type=\u0000\u0000\u0000\u0000"},{"message":"Invalid ID3v2.3 frame-header-ID: \u0000\u0000\u0000\u0000"},{"message":"id3v2.3 header has empty tag type=\u0000\u0000\u0000\u0000"},{"message":"Invalid ID3v2.3 frame-header-ID: \u0000\u0000\u0000\u0000"},{"message":"id3v2.3 header has empty tag type=\u0000\u0000\u0000\u0000"},{"message":"Invalid ID3v2.3 frame-header-ID: \u0000\u0000\u0000\u0000"},{"message":"id3v2.3 header has empty tag type=\u0000\u0000\u0000\u0000"},{"message":"Invalid ID3v2.3 frame-header-ID: \u0000\u0000\u0000\u0000"},{"message":"id3v2.3 header has empty tag type=\u0000\u0000\u0000\u0000"},{"message":"Invalid ID3v2.3 frame-header-ID: \u0000\u0000\u0000\u0000"},{"message":"id3v2.3 header has empty tag type=\u0000\u0000\u0000\u0000"},{"message":"Invalid ID3v2.3 frame-header-ID: \u0000\u0000\u0000\u0000"},{"message":"id3v2.3 header has empty tag type=\u0000\u0000\u0000\u0000"},{"message":"Invalid ID3v2.3 frame-header-ID: \u0000\u0000\u0000\u0000"},{"message":"id3v2.3 header has empty tag type=\u0000\u0000\u0000\u0000"},{"message":"Invalid ID3v2.3 frame-header-ID: \u0000\u0000\u0000\u0000"},{"message":"id3v2.3 header has empty tag type=\u0000\u0000\u0000\u0000"},{"message":"Invalid ID3v2.3 frame-header-ID: \u0000\u0000\u0000\u0000"},{"message":"id3v2.3 header has empty tag type=\u0000\u0000\u0000\u0000"},{"message":"Invalid ID3v2.3 frame-header-ID: \u0000\u0000\u0000\u0000"},{"message":"id3v2.3 header has empty tag type=\u0000\u0000\u0000\u0000"},{"message":"Invalid ID3v2.3 frame-header-ID: \u0000\u0000\u0000\u0000"},{"message":"id3v2.3 header has empty tag type=\u0000\u0000\u0000\u0000"},{"message":"Invalid ID3v2.3 frame-header-ID: \u0000\u0000\u0000\u0000"},{"message":"id3v2.3 header has empty tag type=\u0000\u0000\u0000\u0000"},{"message":"Invalid ID3v2.3 frame-header-ID: \u0000\u0000\u0000\u0000"},{"message":"id3v2.3 header has empty tag type=\u0000\u0000\u0000\u0000"},{"message":"Invalid ID3v2.3 frame-header-ID: \u0000\u0000\u0000\u0000"},{"message":"id3v2.3 header has empty tag type=\u0000\u0000\u0000\u0000"},{"message":"Invalid ID3v2.3 frame-header-ID: \u0000\u0000\u0000\u0000"},{"message":"id3v2.3 header has empty tag type=\u0000\u0000\u0000\u0000"},{"message":"Invalid ID3v2.3 frame-header-ID: \u0000\u0000\u0000\u0000"},{"message":"id3v2.3 header has empty tag type=\u0000\u0000\u0000\u0000"},{"message":"Invalid ID3v2.3 frame-header-ID: \u0000\u0000\u0000\u0000"},{"message":"id3v2.3 header has empty tag type=\u0000\u0000\u0000\u0000"},{"message":"Invalid ID3v2.3 frame-header-ID: \u0000\u0000\u0000\u0000"},{"message":"id3v2.3 header has empty tag type=\u0000\u0000\u0000\u0000"},{"message":"Invalid ID3v2.3 frame-header-ID: \u0000\u0000\u0000\u0000"},{"message":"id3v2.3 header has empty tag type=\u0000\u0000\u0000\u0000"},{"message":"Invalid ID3v2.3 frame-header-ID: \u0000\u0000\u0000\u0000"},{"message":"id3v2.3 header has empty tag type=\u0000\u0000\u0000\u0000"},{"message":"Invalid ID3v2.3 frame-header-ID: \u0000\u0000\u0000\u0000"},{"message":"id3v2.3 header has empty tag type=\u0000\u0000\u0000\u0000"},{"message":"Invalid ID3v2.3 frame-header-ID: \u0000\u0000\u0000\u0000"},{"message":"id3v2.3 header has empty tag type=\u0000\u0000\u0000\u0000"},{"message":"Invalid ID3v2.3 frame-header-ID: \u0000\u0000\u0000\u0000"},{"message":"id3v2.3 header has empty tag type=\u0000\u0000\u0000\u0000"},{"message":"Invalid ID3v2.3 frame-header-ID: \u0000\u0000\u0000\u0000"},{"message":"id3v2.3 header has empty tag type=\u0000\u0000\u0000\u0000"},{"message":"Invalid ID3v2.3 frame-header-ID: \u0000\u0000\u0000\u0000"},{"message":"id3v2.3 header has empty tag type=\u0000\u0000\u0000\u0000"},{"message":"Invalid ID3v2.3 frame-header-ID: \u0000\u0000\u0000\u0000"},{"message":"id3v2.3 header has empty tag type=\u0000\u0000\u0000\u0000"},{"message":"Invalid ID3v2.3 frame-header-ID: \u0000\u0000\u0000\u0000"},{"message":"id3v2.3 header has empty tag type=\u0000\u0000\u0000\u0000"},{"message":"Invalid ID3v2.3 frame-header-ID: \u0000\u0000\u0000\u0000"},{"message":"id3v2.3 header has empty tag type=\u0000\u0000\u0000\u0000"},{"message":"Invalid ID3v2.3 frame-header-ID: \u0000\u0000\u0000\u0000"},{"message":"id3v2.3 header has empty tag type=\u0000\u0000\u0000\u0000"},{"message":"Invalid ID3v2.3 frame-header-ID: \u0000\u0000\u0000\u0000"},{"message":"id3v2.3 header has empty tag type=\u0000\u0000\u0000\u0000"},{"message":"Invalid ID3v2.3 frame-header-ID: \u0000\u0000\u0000\u0000"},{"message":"id3v2.3 header has empty tag type=\u0000\u0000\u0000\u0000"},{"message":"Invalid ID3v2.3 frame-header-ID: \u0000\u0000\u0000\u0000"},{"message":"id3v2.3 header has empty tag type=\u0000\u0000\u0000\u0000"},{"message":"Invalid ID3v2.3 frame-header-ID: \u0000\u0000\u0000\u0000"},{"message":"id3v2.3 header has empty tag type=\u0000\u0000\u0000\u0000"},{"message":"Invalid ID3v2.3 frame-header-ID: \u0000\u0000\u0000\u0000"},{"message":"id3v2.3 header has empty tag type=\u0000\u0000\u0000\u0000"},{"message":"Invalid ID3v2.3 frame-header-ID: \u0000\u0000\u0000\u0000"},{"message":"id3v2.3 header has empty tag type=\u0000\u0000\u0000\u0000"},{"message":"Invalid ID3v2.3 frame-header-ID: \u0000\u0000\u0000\u0000"},{"message":"id3v2.3 header has empty tag type=\u0000\u0000\u0000\u0000"},{"message":"Invalid ID3v2.3 frame-header-ID: \u0000\u0000\u0000\u0000"},{"message":"id3v2.3 header has empty tag type=\u0000\u0000\u0000\u0000"},{"message":"Invalid ID3v2.3 frame-header-ID: \u0000\u0000\u0000\u0000"},{"message":"id3v2.3 header has empty tag type=\u0000\u0000\u0000\u0000"},{"message":"Invalid ID3v2.3 frame-header-ID: \u0000\u0000\u0000\u0000"},{"message":"id3v2.3 header has empty tag type=\u0000\u0000\u0000\u0000"},{"message":"Illegal ID3v2 tag length"}]},"common":{"track":{"no":7,"of":null},"disk":{"no":null,"of":null},"movementIndex":{"no":null,"of":null},"year":null,"artists":["J. Mono"],"artist":"J. Mono","title":"Into the Sun Pt 5","album":"The Cold Lamper / J. Mono Split"}}