{"metadata":{"format":{"tagTypes":["APEv2"],"trackInfo":[],"lossless":false,"container":"MPEG","codec":"MPEG 1 Layer 3","sampleRate":44100,"numberOfChannels":2,"bitrate":160000,"codecProfile":"CBR","numberOfSamples":4096512,"duration":92.89142857142858},"native":{"APEv2":[{"id":"ALBUM","value":"Daisy Chain"},{"id":"ARTIST","value":"Snitcherz"},{"id":"COMPOSER","value":"Leah Greenberg"},{"id":"TITLE","value":"Blow Me"},{"id":"TRACK","value":"2"}]},"quality":{"warnings":[]},"common":{"track":{"no":2,"of":null},"disk":{"no":null,"of":null},"movementIndex":{"no":null,"of":null},"album":"Daisy Chain","artists":["Snitcherz"],"artist":"Snitcherz","composer":["Leah Greenberg"],"title":"Blow Me"}},"name":"Blow Me","slug":"blow-me","path":"/artists/snitcherz/daisy-chain/blow-me","filePath":"snitcherz/daisy-chain/02-Blow-Me.mp3","artistName":"Snitcherz","artistSlug":"snitcherz","artistPath":"/artists/snitcherz","albumName":"Daisy Chain","albumSlug":"daisy-chain","albumPath":"/artists/snitcherz/daisy-chain","members":[{"name":"Leah Greenberg","slug":"leah-greenberg","path":"/members/leah-greenberg"}]}