{"metadata":{"format":{"tagTypes":["APEv2"],"trackInfo":[],"lossless":false,"container":"MPEG","codec":"MPEG 1 Layer 3","sampleRate":44100,"numberOfChannels":2,"bitrate":128000,"codecProfile":"CBR","numberOfSamples":12859776,"duration":291.6048979591837},"native":{"APEv2":[{"id":"ALBUM","value":"Happybear Kaboom / Father Sleep Split"},{"id":"ARTIST","value":"Father Sleep"},{"id":"COMPOSER","value":"Jared Brey"},{"id":"COMPOSER","value":"Curt Howard"},{"id":"TITLE","value":"There is a Mirror in the Middle"},{"id":"TRACK","value":"4"}]},"quality":{"warnings":[]},"common":{"track":{"no":4,"of":null},"disk":{"no":null,"of":null},"movementIndex":{"no":null,"of":null},"album":"Happybear Kaboom / Father Sleep Split","artists":["Father Sleep"],"artist":"Father Sleep","composer":["Jared Brey","Curt Howard"],"title":"There is a Mirror in the Middle"}},"name":"There is a Mirror in the Middle","path":"/artists/father-sleep/happybear-kaboom-father-sleep-split/there-is-a-mirror-in-the-middle","filePath":"/_SPLITS/happybear-kaboom-father-sleep/04-There-is-a-Mirror-in-the-Middle.mp3","artistName":"Father Sleep","artistPath":"/artists/father-sleep","albumName":"Happybear Kaboom / Father Sleep Split","albumPath":"/artists/father-sleep/happybear-kaboom-father-sleep-split","members":[{"name":"Jared Brey","path":"/members/jared-brey"},{"name":"Curt Howard","path":"/members/curt-howard"}],"trackNumber":4}