{"metadata":{"format":{"tagTypes":["APEv2"],"trackInfo":[],"lossless":false,"container":"MPEG","codec":"MPEG 1 Layer 3","sampleRate":44100,"numberOfChannels":2,"bitrate":192000,"tool":"LAME 3.93UU","codecProfile":"CBR","numberOfSamples":8766720,"duration":198.79183673469387},"native":{"APEv2":[{"id":"ALBUM","value":"Folktales"},{"id":"ARTIST","value":"Red Rocket"},{"id":"COMPOSER","value":"John Vogel"},{"id":"COMPOSER","value":"Russell Brodie"},{"id":"COMPOSER","value":"Tris Palazzalo"},{"id":"COMPOSER","value":"Roman Saléve"},{"id":"COMPOSER","value":"Adam Katz"},{"id":"TITLE","value":"Grace Period"},{"id":"TRACK","value":"2"}]},"quality":{"warnings":[]},"common":{"track":{"no":2,"of":null},"disk":{"no":null,"of":null},"movementIndex":{"no":null,"of":null},"album":"Folktales","artists":["Red Rocket"],"artist":"Red Rocket","composer":["John Vogel","Russell Brodie","Tris Palazzalo","Roman Saléve","Adam Katz"],"title":"Grace Period"}},"name":"Grace Period","slug":"grace-period","path":"/artists/red-rocket/folktales/grace-period","filePath":"red-rocket/folktales/02-Grace-Period.mp3","artistName":"Red Rocket","artistSlug":"red-rocket","artistPath":"/artists/red-rocket","albumName":"Folktales","albumSlug":"folktales","albumPath":"/artists/red-rocket/folktales","members":[{"name":"John Vogel","slug":"john-vogel","path":"/members/john-vogel"},{"name":"Russell Brodie","slug":"russell-brodie","path":"/members/russell-brodie"},{"name":"Tris Palazzalo","slug":"tris-palazzalo","path":"/members/tris-palazzalo"},{"name":"Roman Saléve","slug":"roman-saleve","path":"/members/roman-saleve"},{"name":"Adam Katz","slug":"adam-katz","path":"/members/adam-katz"}]}