{"format":{"tagTypes":["APEv2"],"trackInfo":[],"lossless":false,"container":"MPEG","codec":"MPEG 1 Layer 3","sampleRate":44100,"numberOfChannels":2,"bitrate":192000,"codecProfile":"CBR","numberOfSamples":8955648,"duration":203.07591836734693},"native":{"APEv2":[{"id":"ALBUM","value":"Dead"},{"id":"ARTIST","value":"Captain Werewolf"},{"id":"TITLE","value":"Lady Boys"},{"id":"TRACK","value":"2"}]},"quality":{"warnings":[]},"common":{"track":{"no":2,"of":null},"disk":{"no":null,"of":null},"movementIndex":{"no":null,"of":null},"album":"Dead","artists":["Captain Werewolf"],"artist":"Captain Werewolf","title":"Lady Boys"}}